MANIFEST.in
setup.py
cstar_perf/__init__.py
cstar_perf.frontend.egg-info/PKG-INFO
cstar_perf.frontend.egg-info/SOURCES.txt
cstar_perf.frontend.egg-info/dependency_links.txt
cstar_perf.frontend.egg-info/entry_points.txt
cstar_perf.frontend.egg-info/namespace_packages.txt
cstar_perf.frontend.egg-info/not-zip-safe
cstar_perf.frontend.egg-info/requires.txt
cstar_perf.frontend.egg-info/top_level.txt
cstar_perf/frontend/__init__.py
cstar_perf/frontend/client/__init__.py
cstar_perf/frontend/client/client.py
cstar_perf/frontend/lib/__init__.py
cstar_perf/frontend/lib/crypto.py
cstar_perf/frontend/lib/server.py
cstar_perf/frontend/lib/socket_comms.py
cstar_perf/frontend/lib/util.py
cstar_perf/frontend/server/__init__.py
cstar_perf/frontend/server/app.py
cstar_perf/frontend/server/cluster_api.py
cstar_perf/frontend/server/controllers.py
cstar_perf/frontend/server/debug.py
cstar_perf/frontend/server/email_notifications.py
cstar_perf/frontend/server/filters.py
cstar_perf/frontend/server/model.py
cstar_perf/frontend/server/notifications.py
cstar_perf/frontend/server/rapid.py
cstar_perf/frontend/server/simple.py
cstar_perf/frontend/server/template_context.py
cstar_perf/frontend/server/util.py
cstar_perf/frontend/server/templates/access_denied.jinja2.html
cstar_perf/frontend/server/templates/cluster.jinja2.html
cstar_perf/frontend/server/templates/graph.jinja2.html
cstar_perf/frontend/server/templates/index.jinja2.html
cstar_perf/frontend/server/templates/layout.jinja2.html
cstar_perf/frontend/server/templates/render.py
cstar_perf/frontend/server/templates/schedule.jinja2.html
cstar_perf/frontend/server/templates/test_macro.jinja2.html
cstar_perf/frontend/server/templates/tests.jinja2.html
cstar_perf/frontend/server/templates/user.jinja2.html
cstar_perf/frontend/server/templates/view_test.jinja2.html
cstar_perf/frontend/server/templates/email/test_status_update.jinja2
cstar_perf/frontend/server/tests/__init__.py
cstar_perf/frontend/server/tests/test_model.py
cstar_perf/frontend/static/index.html
cstar_perf/frontend/static/css/app.css
cstar_perf/frontend/static/css/bootstrap-responsive.css
cstar_perf/frontend/static/graph/css/style.css
cstar_perf/frontend/static/graph/js/graph.js
cstar_perf/frontend/static/graph/js/parseuri.js
cstar_perf/frontend/static/img/datastax.png
cstar_perf/frontend/static/js/app.js
