Metadata-Version: 1.0
Name: cstar-perf.frontend
Version: 1.0
Summary: A web frontend for cstar_perf, the Cassandra performance testing platform
Home-page: https://github.com/datastax/cstar_perf
Author: The DataStax Cassandra Test Engineering Team
Author-email: ryan@datastax.com
License: UNKNOWN
Platform: UNKNOWN
